{
  "generated_at": "2026-05-04T22:32:50Z",
  "total_items": 500,
  "by_severity": {
    "critical": 11,
    "high": 66,
    "low": 75,
    "medium": 348
  },
  "by_source": {
    "bleeping": 46,
    "cisa-kev": 6,
    "ipa-alert": 2,
    "jpcert-wr": 5,
    "krebs": 1,
    "msrc": 7,
    "nvd-recent": 343,
    "rapid7": 8,
    "sans-isc": 14,
    "schneier": 8,
    "thehackernews": 51,
    "trailofbits": 1,
    "zdi": 8
  },
  "by_category": {
    "advisory": 14,
    "analysis": 8,
    "news": 112,
    "research": 9,
    "vuln": 357
  },
  "top_vendors": [
    {
      "key": "linux",
      "count": 68
    },
    {
      "key": "wordpress",
      "count": 43
    },
    {
      "key": "wireshark",
      "count": 39
    },
    {
      "key": "microsoft",
      "count": 33
    },
    {
      "key": "github",
      "count": 13
    },
    {
      "key": "openclaw",
      "count": 13
    },
    {
      "key": "freebsd",
      "count": 6
    },
    {
      "key": "adobe",
      "count": 5
    },
    {
      "key": "amazon",
      "count": 5
    },
    {
      "key": "firefox",
      "count": 5
    }
  ],
  "top_tags": [
    {
      "key": "watch",
      "count": 157
    },
    {
      "key": "linux",
      "count": 65
    },
    {
      "key": "rce",
      "count": 64
    },
    {
      "key": "wordpress",
      "count": 43
    },
    {
      "key": "microsoft",
      "count": 33
    },
    {
      "key": "xss",
      "count": 22
    },
    {
      "key": "critical-cvss",
      "count": 21
    },
    {
      "key": "sqli",
      "count": 19
    },
    {
      "key": "actively-exploited",
      "count": 16
    },
    {
      "key": "auth-bypass",
      "count": 16
    },
    {
      "key": "lpe",
      "count": 14
    },
    {
      "key": "github",
      "count": 13
    },
    {
      "key": "malware",
      "count": 13
    },
    {
      "key": "path-traversal",
      "count": 12
    },
    {
      "key": "kev",
      "count": 6
    }
  ],
  "last_24h_count": 21,
  "critical_last_7d": 9
}
